cv_tools/__init__.py
pillow_tools/__init__.py
torch_tools/__init__.py
lth_develop_tools-0.0.0.dist-info/METADATA
lth_develop_tools-0.0.0.dist-info/WHEEL
lth_develop_tools-0.0.0.dist-info/top_level.txt
lth_develop_tools-0.0.0.dist-info/RECORD
