Metadata-Version: 2.1
Name: lth-develop-tools
Version: 0.0.0
Summary: this package is used for author only
Home-page: UNKNOWN
Author: lth
Author-email: 673567903@qq.com
License: UNKNOWN
Platform: UNKNOWN
Classifier: Programming Language :: Python :: 3
Classifier: License :: OSI Approved :: MIT License
Classifier: Operating System :: OS Independent
Requires-Python: >=3.6
